arxivsummary/__init__.py
arxivsummary/__main__.py
arxivsummary/arxivsummary.py
arxivsummary-0.3.dist-info/entry_points.txt
arxivsummary-0.3.dist-info/LICENSE
arxivsummary-0.3.dist-info/WHEEL
arxivsummary-0.3.dist-info/METADATA
arxivsummary-0.3.dist-info/RECORD
