Metadata-Version: 2.1
Name: arxivsummary
Version: 0.3
Summary: arxivsummary - Arxiv summary report generator. 
Author-email: Graham Wheeler <graham@grahamwheeler.com>
Classifier: Intended Audience :: Science/Research
Classifier: License :: OSI Approved :: MIT License
Classifier: Programming Language :: Python :: 3
Classifier: Topic :: Utilities
Requires-Dist: openai==1.57.4
Requires-Dist: flit_core==3.9.0
Requires-Dist: click==8.1.7
Project-URL: Source, https://github.com/gramster/arxivsummary
